farad/__init__.py
farad/driver.py
farad/dual.py
farad/elem.py
farad/rnode.py
farad-1.2.dist-info/LICENSE
farad-1.2.dist-info/METADATA
farad-1.2.dist-info/WHEEL
farad-1.2.dist-info/top_level.txt
farad-1.2.dist-info/RECORD
