Metadata-Version: 2.1
Name: farad
Version: 1.2
Summary: A package for forward and reverse automatic differentiation
Home-page: https://github.com/The-Pyoneers/cs107-FinalProject
Author: Harvard CS107 Final Project Group 34
Author-email: UNKNOWN
License: UNKNOWN
Platform: UNKNOWN
Classifier: Programming Language :: Python :: 3
Classifier: License :: OSI Approved :: MIT License
Classifier: Operating System :: OS Independent
Requires-Dist: numpy
